pyoneer_vsx/__init__.py
pyoneer_vsx/connection.py
pyoneer_vsx/receiver.py
pyoneer_vsx-0.0.3.dist-info/LICENSE
pyoneer_vsx-0.0.3.dist-info/METADATA
pyoneer_vsx-0.0.3.dist-info/WHEEL
pyoneer_vsx-0.0.3.dist-info/top_level.txt
pyoneer_vsx-0.0.3.dist-info/RECORD
