Metadata-Version: 2.1
Name: pyoneer-vsx
Version: 0.0.3
Summary: A python library to control Pioneer VSX AVRs over telnet
Home-page: https://github.com/j-mutter/pyoneer_vsx
Author: Justin Mutter
License: UNKNOWN
Platform: UNKNOWN
Classifier: Development Status :: 2 - Pre-Alpha
Classifier: Intended Audience :: Developers
Classifier: License :: OSI Approved :: Apache Software License
Classifier: Operating System :: OS Independent
Classifier: Programming Language :: Python :: 3
Classifier: Topic :: Home Automation
Classifier: Topic :: Multimedia :: Sound/Audio
